GBARpy/MCPPicture.py
GBARpy/Main_window.py
GBARpy/__init__.py
GBARpy/__main__.py
GBARpy/static/BGT_in.mcp
GBARpy/static/BGT_out.mcp
GBARpy/static/GBAR_logo.png
GBARpy/static/HFT_out.mcp
GBARpy/static/left.png
GBARpy/static/right.png
GBARpy-1.2.0.dist-info/LICENSE
GBARpy-1.2.0.dist-info/METADATA
GBARpy-1.2.0.dist-info/WHEEL
GBARpy-1.2.0.dist-info/top_level.txt
GBARpy-1.2.0.dist-info/RECORD
