Metadata-Version: 2.1
Name: GBARpy
Version: 1.2.0
Summary: Libraries and software to analyse data (the MCP's picture and CsI signals) in the framework of the GBAR experiment
Home-page: https://github.com/sniang/GBARpy
Author: Samuel Niang
Author-email: samuel.niang@cern.ch
License: UNKNOWN
Project-URL: Bug Tracker, https://github.com/sniang/GBARpy/issues
Platform: UNKNOWN
Classifier: Programming Language :: Python :: 3
Classifier: License :: OSI Approved :: MIT License
Classifier: Operating System :: OS Independent
Requires-Python: >=3.6
License-File: LICENSE
Requires-Dist: numpy
Requires-Dist: matplotlib
Requires-Dist: scipy
Requires-Dist: scikit-image
Requires-Dist: dill
